{
    "99": {
        "title": "7 дней",
        "name": "Подписка на 7 дней",
        "secure_name": "7days",
        "prices": {
            "usd": 2.5,
            "uah": 99,
            "rub": 169
        },
        "duration": 7
    },
    "100": {
        "title": "14 дней",
        "name": "Подписка на 14 дней",
        "secure_name": "14days",
        "prices": {
            "usd": 3.5,
            "uah": 149,
            "rub": 259
        },
        "duration": 14
    },
    "101": {
        "title": "1 Месяц",
        "name": "Подписка на 1 месяц",
        "secure_name": "1mon",
        "prices": {
            "usd": 4.5,
            "uah": 199,
            "rub": 349
        },
        "duration": 30
    },
    "105": {
        "title": "Lifetime",
        "name": "Подписка Навсегда",
        "secure_name": "life",
        "prices": {
            "usd": 22.5,
            "uah": 999,
            "rub": 1699
        },
        "color": "#f1c40f",
        "duration": 36500
    }
}